MANIFEST.in
README.md
requirements.txt
setup.cfg
setup.py
versioneer.py
botcity/plugins/crawler/__init__.py
botcity/plugins/crawler/_version.py
botcity/plugins/crawler/html.py
botcity/plugins/crawler/plugin.py
botcity_crawler_plugin.egg-info/PKG-INFO
botcity_crawler_plugin.egg-info/SOURCES.txt
botcity_crawler_plugin.egg-info/dependency_links.txt
botcity_crawler_plugin.egg-info/requires.txt
botcity_crawler_plugin.egg-info/top_level.txt