Metadata-Version: 2.1
Name: botcity-crawler-plugin
Version: 0.2.2
Home-page: https://bitbucket.org/botcitydev/bot-crawler-plugin-python.git
Requires-Python: >=3.7
